octo_pipeline_python/backends/blackduck/__init__.py
octo_pipeline_python/backends/blackduck/blackduck_backend.py
octo_pipeline_python/backends/blackduck/actions/__init__.py
octo_pipeline_python/backends/blackduck/actions/blackduck_detect.py
octo_pipeline_python/backends/blackduck/actions/blackduck_verify.py
octo_pipeline_python/backends/blackduck/models/__init__.py
octo_pipeline_python/backends/blackduck/models/blackduck_model.py
octo_pipeline_backend_blackduck_python-1.3.2.dist-info/LICENSE.txt
octo_pipeline_backend_blackduck_python-1.3.2.dist-info/METADATA
octo_pipeline_backend_blackduck_python-1.3.2.dist-info/README.md
octo_pipeline_backend_blackduck_python-1.3.2.dist-info/WHEEL
octo_pipeline_backend_blackduck_python-1.3.2.dist-info/top_level.txt
octo_pipeline_backend_blackduck_python-1.3.2.dist-info/RECORD
