Metadata-Version: 2.1
Name: octo-pipeline-backend-blackduck-python
Version: 1.3.2
Summary: blackduck backend implementation for octo-pipeline
Home-page: https://github.com/ofiriluz/octo-pipeline-python
Author: Ofir Iluz
Author-email: iluzofir@gmail.com
License: MIT
Classifier: Intended Audience :: Developers
Classifier: Natural Language :: English
Classifier: Programming Language :: Python
Classifier: Programming Language :: Python :: 3.8
Classifier: Programming Language :: Python :: 3.9
Classifier: Programming Language :: Python :: 3.10
Requires-Python: >= 3.8
License-File: LICENSE.txt
License-File: README.md
Requires-Dist: Requests
Requires-Dist: blackduck
Requires-Dist: octo-pipeline-python
Requires-Dist: packaging
Requires-Dist: octo_pipeline_python
Requires-Dist: pydantic
Requires-Dist: overrides
